README.md
setup.cfg
setup.py
distributions/Binomialdistribution.py
distributions/Gaussiandistribution.py
distributions/Generaldistribution.py
distributions/__init__.py
wjsunny_distributions.egg-info/PKG-INFO
wjsunny_distributions.egg-info/SOURCES.txt
wjsunny_distributions.egg-info/dependency_links.txt
wjsunny_distributions.egg-info/not-zip-safe
wjsunny_distributions.egg-info/top_level.txt